__init__.py
harness.py
input_output_test-0.0.1.dist-info/LICENSE
input_output_test-0.0.1.dist-info/METADATA
input_output_test-0.0.1.dist-info/WHEEL
input_output_test-0.0.1.dist-info/top_level.txt
input_output_test-0.0.1.dist-info/RECORD
